psytricks/__init__.py
psytricks/__ps1__/psytricks-lib.ps1
psytricks/__ps1__/psytricks-wrapper.ps1
psytricks/__ps1__/restricks-server.example.xml
psytricks/__ps1__/restricks-server.ps1
psytricks/__ps1__/sampledata/GetAccessUsers.json
psytricks/__ps1__/sampledata/GetMachineStatus.json
psytricks/__ps1__/sampledata/GetSessions.json
psytricks/cli.py
psytricks/decoder.py
psytricks/literals.py
psytricks/mappings.py
psytricks/wrapper.py
psytricks-2.1.6.dist-info/LICENSE
psytricks-2.1.6.dist-info/METADATA
psytricks-2.1.6.dist-info/WHEEL
psytricks-2.1.6.dist-info/entry_points.txt
psytricks-2.1.6.dist-info/RECORD
