Metadata-Version: 2.1
Name: psytricks
Version: 2.1.6
Summary: PowerShell Python Citrix Tricks.
License: GPL-3.0-or-later
Author: Niko Ehrenfeuchter
Author-email: nikolaus.ehrenfeuchter@unibas.ch
Requires-Python: >=3.9,<4.0
Classifier: License :: OSI Approved :: GNU General Public License v3 or later (GPLv3+)
Classifier: Programming Language :: Python :: 3
Classifier: Programming Language :: Python :: 3.9
Classifier: Programming Language :: Python :: 3.10
Classifier: Programming Language :: Python :: 3.11
Requires-Dist: click (>=8.1.3,<9.0.0)
Requires-Dist: loguru (>=0.7.0,<0.8.0)
Requires-Dist: requests (>=2.30.0,<3.0.0)
Project-URL: Changelog, https://github.com/imcf/psytricks/blob/main/CHANGELOG.md
Project-URL: Documentation, https://imcf.one/apidocs/psytricks/psytricks.html
Project-URL: Organisation Homepage, https://imcf.one/
Project-URL: Twitter, https://twitter.com/imcf_basel
